{
  "number": 280,
  "name_devanagari": "पद्मनाभसहोदरी",
  "name_transliterated": "Padmanābha-sahodarī",
  "meaning": "She is the sister of Vishnu (Padmanābha). It implies that along with Vishnu, She takes on the responsibility of sustenance of this creation.",
  "commentary": "In the Puri Jagannatha temple, the siblings Krishna, Balarama and Subhadra are worshipped. During the incarnation of Krishna, She appeared twice- at first She was born to Vasudeva and Devaki (parents of Krishna) as Yogamāya to protect Baby Krishna from the clutches of demon Kamsa and later on She was born to the same couple as Subhadra.\n\nWith this name Bhairavi upasana is complete."
}