{
  "number": 478,
  "name_devanagari": "खट्वाङ्गादिप्रहरणा",
  "name_transliterated": "Khatvāngādi praharana-",
  "meaning": "Holding the ‘khatvānga’ and other weapons in Her hand, She is guarding (praharana) the foetus during its first month of growth.",
  "commentary": "Khatvānga is the long club-like instrument fitted with a skull on its head. Apart from the Khatvānga, the other weapons that She holds are khadga (sword), charma (skin) and trishula (trident).\n\nThis name subtly implies that She blesses the foetus with a head. By the time the foetus is one-month-old its head and skin are formed."
}